{
  "name": "bed",
  "version": "3.0.1",
  "arch": "aarch64",
  "maintainer": "Jaap Korthals Altes",
  "description": "Adjustable data format binary editor",
  "provides": ["bed"],
  "files" : {
"termux-root/data/data/com.termux/files/usr/": "",
"termux-root/data/data/com.termux/files/usr/bin": "bin",
"termux-root/data/data/com.termux/files/usr/bin/bed": "bin/bed",
"termux-root/data/data/com.termux/files/usr/lib": "lib",
"termux-root/data/data/com.termux/files/usr/lib/bed-3.0.1": "lib/bed-3.0.1",
"termux-root/data/data/com.termux/files/usr/lib/bed-3.0.1/README": "lib/bed-3.0.1/README",
"termux-root/data/data/com.termux/files/usr/lib/bed-3.0.1/bedrc": "lib/bed-3.0.1/bedrc",
"termux-root/data/data/com.termux/files/usr/lib/bed-3.0.1/testmarks.bedm": "lib/bed-3.0.1/testmarks.bedm",
"termux-root/data/data/com.termux/files/usr/lib/bed-3.0.1/utils": "lib/bed-3.0.1/utils",
"termux-root/data/data/com.termux/files/usr/lib/bed-3.0.1/utils/bin2byte": "lib/bed-3.0.1/utils/bin2byte",
"termux-root/data/data/com.termux/files/usr/lib/bed-3.0.1/utils/bin2byte.c": "lib/bed-3.0.1/utils/bin2byte.c",
"termux-root/data/data/com.termux/files/usr/lib/bed-3.0.1/utils/keyconfig": "lib/bed-3.0.1/utils/keyconfig",
"termux-root/data/data/com.termux/files/usr/lib/bed-3.0.1/utils/features.h": "lib/bed-3.0.1/utils/features.h",
"termux-root/data/data/com.termux/files/usr/lib/bed-3.0.1/misc": "lib/bed-3.0.1/misc",
"termux-root/data/data/com.termux/files/usr/lib/bed-3.0.1/misc/elfheader64.bedda": "lib/bed-3.0.1/misc/elfheader64.bedda",
"termux-root/data/data/com.termux/files/usr/lib/bed-3.0.1/misc/elfheader32.bedda": "lib/bed-3.0.1/misc/elfheader32.bedda",
"termux-root/data/data/com.termux/files/usr/lib/bed-3.0.1/misc/dynsym.bedda": "lib/bed-3.0.1/misc/dynsym.bedda",
"termux-root/data/data/com.termux/files/usr/lib/bed-3.0.1/misc/filepermissionbits.bedda": "lib/bed-3.0.1/misc/filepermissionbits.bedda",
"termux-root/data/data/com.termux/files/usr/lib/bed-3.0.1/misc/char2.bedda": "lib/bed-3.0.1/misc/char2.bedda",
"termux-root/data/data/com.termux/files/usr/lib/bed-3.0.1/misc/programheaderELF32.bedda": "lib/bed-3.0.1/misc/programheaderELF32.bedda",
"termux-root/data/data/com.termux/files/usr/lib/bed-3.0.1/misc/README.txt": "lib/bed-3.0.1/misc/README.txt",
"termux-root/data/data/com.termux/files/usr/lib/bed-3.0.1/misc/pushlpushl.bedda": "lib/bed-3.0.1/misc/pushlpushl.bedda",
"termux-root/data/data/com.termux/files/usr/lib/bed-3.0.1/misc/win32sections.bedda": "lib/bed-3.0.1/misc/win32sections.bedda",
"termux-root/data/data/com.termux/files/usr/lib/bed-3.0.1/misc/symtab.bedda": "lib/bed-3.0.1/misc/symtab.bedda",
"termux-root/data/data/com.termux/files/usr/lib/bed-3.0.1/misc/char2b.bedda": "lib/bed-3.0.1/misc/char2b.bedda",
"termux-root/data/data/com.termux/files/usr/lib/bed-3.0.1/misc/hexasc.bedda": "lib/bed-3.0.1/misc/hexasc.bedda",
"termux-root/data/data/com.termux/files/usr/lib/bed-3.0.1/misc/sectionheader.bedda": "lib/bed-3.0.1/misc/sectionheader.bedda",
"termux-root/data/data/com.termux/files/usr/lib/bed-3.0.1/misc/programheaderELF64.bedda": "lib/bed-3.0.1/misc/programheaderELF64.bedda",
"termux-root/data/data/com.termux/files/usr/lib/bed-3.0.1/bedmagic.short": "lib/bed-3.0.1/bedmagic.short",
"termux-root/data/data/com.termux/files/usr/lib/bed-3.0.1/terminfo": "lib/bed-3.0.1/terminfo",
"termux-root/data/data/com.termux/files/usr/lib/bed-3.0.1/terminfo/v": "lib/bed-3.0.1/terminfo/v",
"termux-root/data/data/com.termux/files/usr/lib/bed-3.0.1/terminfo/v/vt100": "lib/bed-3.0.1/terminfo/v/vt100",
"termux-root/data/data/com.termux/files/usr/lib/bed-3.0.1/terminfo/l": "lib/bed-3.0.1/terminfo/l",
"termux-root/data/data/com.termux/files/usr/lib/bed-3.0.1/terminfo/l/linux": "lib/bed-3.0.1/terminfo/l/linux",
"termux-root/data/data/com.termux/files/usr/lib/bed-3.0.1/terminfo/x": "lib/bed-3.0.1/terminfo/x",
"termux-root/data/data/com.termux/files/usr/lib/bed-3.0.1/terminfo/x/xterm-256color": "lib/bed-3.0.1/terminfo/x/xterm-256color",
"termux-root/data/data/com.termux/files/usr/lib/bed-3.0.1/terminfo/x/xterm": "lib/bed-3.0.1/terminfo/x/xterm",
"termux-root/data/data/com.termux/files/usr/lib/bed-3.0.1/terminfo/r": "lib/bed-3.0.1/terminfo/r",
"termux-root/data/data/com.termux/files/usr/lib/bed-3.0.1/terminfo/r/rxvt": "lib/bed-3.0.1/terminfo/r/rxvt",
"termux-root/data/data/com.termux/files/usr/lib/bed-3.0.1/terminfo/r/rxvtbed": "lib/bed-3.0.1/terminfo/r/rxvtbed",
"termux-root/data/data/com.termux/files/usr/lib/bed-3.0.1/terminfo/s": "lib/bed-3.0.1/terminfo/s",
"termux-root/data/data/com.termux/files/usr/lib/bed-3.0.1/terminfo/s/screen-256color": "lib/bed-3.0.1/terminfo/s/screen-256color",
"termux-root/data/data/com.termux/files/usr/lib/bed-3.0.1/terminfo/s/screen": "lib/bed-3.0.1/terminfo/s/screen",
"termux-root/data/data/com.termux/files/usr/lib/bed-3.0.1/build": "lib/bed-3.0.1/build",
"termux-root/data/data/com.termux/files/usr/lib/bed-3.0.1/LICENSE": "lib/bed-3.0.1/LICENSE",
"termux-root/data/data/com.termux/files/usr/lib/bed-3.0.1/config": "lib/bed-3.0.1/config",
"termux-root/data/data/com.termux/files/usr/lib/bed-3.0.1/plugins": "lib/bed-3.0.1/plugins",
"termux-root/data/data/com.termux/files/usr/lib/bed-3.0.1/plugins/screenpart.h": "lib/bed-3.0.1/plugins/screenpart.h",
"termux-root/data/data/com.termux/files/usr/lib/bed-3.0.1/plugins/filter.h": "lib/bed-3.0.1/plugins/filter.h",
"termux-root/data/data/com.termux/files/usr/lib/bed-3.0.1/plugins/repeat.h": "lib/bed-3.0.1/plugins/repeat.h",
"termux-root/data/data/com.termux/files/usr/lib/bed-3.0.1/plugins/multidigit.h": "lib/bed-3.0.1/plugins/multidigit.h",
"termux-root/data/data/com.termux/files/usr/lib/bed-3.0.1/plugins/contain.h": "lib/bed-3.0.1/plugins/contain.h",
"termux-root/data/data/com.termux/files/usr/lib/bed-3.0.1/plugins/global.h": "lib/bed-3.0.1/plugins/global.h",
"termux-root/data/data/com.termux/files/usr/lib/bed-3.0.1/plugins/defines.h": "lib/bed-3.0.1/plugins/defines.h",
"termux-root/data/data/com.termux/files/usr/lib/bed-3.0.1/plugins/readconfig.h": "lib/bed-3.0.1/plugins/readconfig.h",
"termux-root/data/data/com.termux/files/usr/lib/bed-3.0.1/plugins/examples": "lib/bed-3.0.1/plugins/examples",
"termux-root/data/data/com.termux/files/usr/lib/bed-3.0.1/plugins/examples/bitflags.cc": "lib/bed-3.0.1/plugins/examples/bitflags.cc",
"termux-root/data/data/com.termux/files/usr/lib/bed-3.0.1/plugins/examples/putselect.cc": "lib/bed-3.0.1/plugins/examples/putselect.cc",
"termux-root/data/data/com.termux/files/usr/lib/bed-3.0.1/plugins/examples/nextitem.cpp": "lib/bed-3.0.1/plugins/examples/nextitem.cpp",
"termux-root/data/data/com.termux/files/usr/lib/bed-3.0.1/plugins/examples/floatdef.h": "lib/bed-3.0.1/plugins/examples/floatdef.h",
"termux-root/data/data/com.termux/files/usr/lib/bed-3.0.1/plugins/examples/time.cpp": "lib/bed-3.0.1/plugins/examples/time.cpp",
"termux-root/data/data/com.termux/files/usr/lib/bed-3.0.1/plugins/examples/subtract.cc": "lib/bed-3.0.1/plugins/examples/subtract.cc",
"termux-root/data/data/com.termux/files/usr/lib/bed-3.0.1/plugins/examples/disass-use": "lib/bed-3.0.1/plugins/examples/disass-use",
"termux-root/data/data/com.termux/files/usr/lib/bed-3.0.1/plugins/examples/crc.c": "lib/bed-3.0.1/plugins/examples/crc.c",
"termux-root/data/data/com.termux/files/usr/lib/bed-3.0.1/plugins/examples/char2.plug": "lib/bed-3.0.1/plugins/examples/char2.plug",
"termux-root/data/data/com.termux/files/usr/lib/bed-3.0.1/plugins/examples/macro2plug.sh": "lib/bed-3.0.1/plugins/examples/macro2plug.sh",
"termux-root/data/data/com.termux/files/usr/lib/bed-3.0.1/plugins/examples/title.cc": "lib/bed-3.0.1/plugins/examples/title.cc",
"termux-root/data/data/com.termux/files/usr/lib/bed-3.0.1/plugins/examples/datatypeinfo.cc": "lib/bed-3.0.1/plugins/examples/datatypeinfo.cc",
"termux-root/data/data/com.termux/files/usr/lib/bed-3.0.1/plugins/examples/translate.cc": "lib/bed-3.0.1/plugins/examples/translate.cc",
"termux-root/data/data/com.termux/files/usr/lib/bed-3.0.1/plugins/examples/oldsigned.h": "lib/bed-3.0.1/plugins/examples/oldsigned.h",
"termux-root/data/data/com.termux/files/usr/lib/bed-3.0.1/plugins/examples/switchsize.cc": "lib/bed-3.0.1/plugins/examples/switchsize.cc",
"termux-root/data/data/com.termux/files/usr/lib/bed-3.0.1/plugins/examples/Makefile": "lib/bed-3.0.1/plugins/examples/Makefile",
"termux-root/data/data/com.termux/files/usr/lib/bed-3.0.1/plugins/examples/elftables32.cc": "lib/bed-3.0.1/plugins/examples/elftables32.cc",
"termux-root/data/data/com.termux/files/usr/lib/bed-3.0.1/plugins/examples/bitcpy.cc": "lib/bed-3.0.1/plugins/examples/bitcpy.cc",
"termux-root/data/data/com.termux/files/usr/lib/bed-3.0.1/plugins/examples/bitfields.cc": "lib/bed-3.0.1/plugins/examples/bitfields.cc",
"termux-root/data/data/com.termux/files/usr/lib/bed-3.0.1/plugins/examples/eventnames.h": "lib/bed-3.0.1/plugins/examples/eventnames.h",
"termux-root/data/data/com.termux/files/usr/lib/bed-3.0.1/plugins/examples/bitcontains.cc": "lib/bed-3.0.1/plugins/examples/bitcontains.cc",
"termux-root/data/data/com.termux/files/usr/lib/bed-3.0.1/plugins/examples/float.cc": "lib/bed-3.0.1/plugins/examples/float.cc",
"termux-root/data/data/com.termux/files/usr/lib/bed-3.0.1/plugins/examples/signed.cc": "lib/bed-3.0.1/plugins/examples/signed.cc",
"termux-root/data/data/com.termux/files/usr/lib/bed-3.0.1/plugins/examples/backward.cc": "lib/bed-3.0.1/plugins/examples/backward.cc",
"termux-root/data/data/com.termux/files/usr/lib/bed-3.0.1/plugins/examples/ebcdic2ascii.h": "lib/bed-3.0.1/plugins/examples/ebcdic2ascii.h",
"termux-root/data/data/com.termux/files/usr/lib/bed-3.0.1/plugins/examples/undoall.cpp": "lib/bed-3.0.1/plugins/examples/undoall.cpp",
"termux-root/data/data/com.termux/files/usr/lib/bed-3.0.1/plugins/examples/cut.cc": "lib/bed-3.0.1/plugins/examples/cut.cc",
"termux-root/data/data/com.termux/files/usr/lib/bed-3.0.1/plugins/examples/unsigned.cpp": "lib/bed-3.0.1/plugins/examples/unsigned.cpp",
"termux-root/data/data/com.termux/files/usr/lib/bed-3.0.1/plugins/examples/duplicate.cpp": "lib/bed-3.0.1/plugins/examples/duplicate.cpp",
"termux-root/data/data/com.termux/files/usr/lib/bed-3.0.1/plugins/examples/disass.plug": "lib/bed-3.0.1/plugins/examples/disass.plug",
"termux-root/data/data/com.termux/files/usr/lib/bed-3.0.1/plugins/examples/edit.cc": "lib/bed-3.0.1/plugins/examples/edit.cc",
"termux-root/data/data/com.termux/files/usr/lib/bed-3.0.1/plugins/examples/helpf1.cc": "lib/bed-3.0.1/plugins/examples/helpf1.cc",
"termux-root/data/data/com.termux/files/usr/lib/bed-3.0.1/plugins/examples/disass.cc": "lib/bed-3.0.1/plugins/examples/disass.cc",
"termux-root/data/data/com.termux/files/usr/lib/bed-3.0.1/plugins/examples/disass-use.c": "lib/bed-3.0.1/plugins/examples/disass-use.c",
"termux-root/data/data/com.termux/files/usr/lib/bed-3.0.1/plugins/examples/chars.c": "lib/bed-3.0.1/plugins/examples/chars.c",
"termux-root/data/data/com.termux/files/usr/lib/bed-3.0.1/plugins/examples/hash.h": "lib/bed-3.0.1/plugins/examples/hash.h",
"termux-root/data/data/com.termux/files/usr/lib/bed-3.0.1/plugins/examples/signed.h": "lib/bed-3.0.1/plugins/examples/signed.h",
"termux-root/data/data/com.termux/files/usr/lib/bed-3.0.1/plugins/examples/ascii2ebcdic.h": "lib/bed-3.0.1/plugins/examples/ascii2ebcdic.h",
"termux-root/data/data/com.termux/files/usr/lib/bed-3.0.1/plugins/examples/skip.cpp": "lib/bed-3.0.1/plugins/examples/skip.cpp",
"termux-root/data/data/com.termux/files/usr/lib/bed-3.0.1/plugins/examples/rxvt.cc": "lib/bed-3.0.1/plugins/examples/rxvt.cc",
"termux-root/data/data/com.termux/files/usr/lib/bed-3.0.1/plugins/examples/newdata.cc": "lib/bed-3.0.1/plugins/examples/newdata.cc",
"termux-root/data/data/com.termux/files/usr/lib/bed-3.0.1/plugins/examples/file.cpp": "lib/bed-3.0.1/plugins/examples/file.cpp",
"termux-root/data/data/com.termux/files/usr/lib/bed-3.0.1/plugins/examples/encodechar.sh": "lib/bed-3.0.1/plugins/examples/encodechar.sh",
"termux-root/data/data/com.termux/files/usr/lib/bed-3.0.1/plugins/examples/ebcdic2ascii.cc": "lib/bed-3.0.1/plugins/examples/ebcdic2ascii.cc",
"termux-root/data/data/com.termux/files/usr/lib/bed-3.0.1/plugins/examples/index2table.cc": "lib/bed-3.0.1/plugins/examples/index2table.cc",
"termux-root/data/data/com.termux/files/usr/lib/bed-3.0.1/plugins/examples/oldsigned.cc": "lib/bed-3.0.1/plugins/examples/oldsigned.cc",
"termux-root/data/data/com.termux/files/usr/lib/bed-3.0.1/plugins/examples/bitfields.h": "lib/bed-3.0.1/plugins/examples/bitfields.h",
"termux-root/data/data/com.termux/files/usr/lib/bed-3.0.1/plugins/examples/searchclip.cc": "lib/bed-3.0.1/plugins/examples/searchclip.cc",
"termux-root/data/data/com.termux/files/usr/lib/bed-3.0.1/plugins/examples/filter.cpp": "lib/bed-3.0.1/plugins/examples/filter.cpp",
"termux-root/data/data/com.termux/files/usr/lib/bed-3.0.1/plugins/examples/install.cc": "lib/bed-3.0.1/plugins/examples/install.cc",
"termux-root/data/data/com.termux/files/usr/lib/bed-3.0.1/plugins/examples/char2.cc": "lib/bed-3.0.1/plugins/examples/char2.cc",
"termux-root/data/data/com.termux/files/usr/lib/bed-3.0.1/plugins/examples/index2table.h": "lib/bed-3.0.1/plugins/examples/index2table.h",
"termux-root/data/data/com.termux/files/usr/lib/bed-3.0.1/plugins/Makefile": "lib/bed-3.0.1/plugins/Makefile",
"termux-root/data/data/com.termux/files/usr/lib/bed-3.0.1/plugins/ascii.h": "lib/bed-3.0.1/plugins/ascii.h",
"termux-root/data/data/com.termux/files/usr/lib/bed-3.0.1/plugins/hassub.h": "lib/bed-3.0.1/plugins/hassub.h",
"termux-root/data/data/com.termux/files/usr/lib/bed-3.0.1/plugins/config.h": "lib/bed-3.0.1/plugins/config.h",
"termux-root/data/data/com.termux/files/usr/lib/bed-3.0.1/plugins/varmacro.h": "lib/bed-3.0.1/plugins/varmacro.h",
"termux-root/data/data/com.termux/files/usr/lib/bed-3.0.1/plugins/dialog.h": "lib/bed-3.0.1/plugins/dialog.h",
"termux-root/data/data/com.termux/files/usr/lib/bed-3.0.1/plugins/faked.h": "lib/bed-3.0.1/plugins/faked.h",
"termux-root/data/data/com.termux/files/usr/lib/bed-3.0.1/plugins/typelist.h": "lib/bed-3.0.1/plugins/typelist.h",
"termux-root/data/data/com.termux/files/usr/lib/bed-3.0.1/plugins/views.h": "lib/bed-3.0.1/plugins/views.h",
"termux-root/data/data/com.termux/files/usr/lib/bed-3.0.1/plugins/plugin.cpp": "lib/bed-3.0.1/plugins/plugin.cpp",
"termux-root/data/data/com.termux/files/usr/lib/bed-3.0.1/plugins/digitstring.h": "lib/bed-3.0.1/plugins/digitstring.h",
"termux-root/data/data/com.termux/files/usr/lib/bed-3.0.1/plugins/screen.h": "lib/bed-3.0.1/plugins/screen.h",
"termux-root/data/data/com.termux/files/usr/lib/bed-3.0.1/plugins/mainprocedures.h": "lib/bed-3.0.1/plugins/mainprocedures.h",
"termux-root/data/data/com.termux/files/usr/lib/bed-3.0.1/plugins/offtypes.h": "lib/bed-3.0.1/plugins/offtypes.h",
"termux-root/data/data/com.termux/files/usr/lib/bed-3.0.1/plugins/type.h": "lib/bed-3.0.1/plugins/type.h",
"termux-root/data/data/com.termux/files/usr/lib/bed-3.0.1/uninstallbed.sh": "lib/bed-3.0.1/uninstallbed.sh",
"termux-root/data/data/com.termux/files/usr/lib/bed-3.0.1/public.pgp": "lib/bed-3.0.1/public.pgp",
"termux-root/data/data/com.termux/files/usr/lib/bed-3.0.1/bedmagic": "lib/bed-3.0.1/bedmagic",
"termux-root/data/data/com.termux/files/usr/lib/bed-3.0.1/addmagic": "lib/bed-3.0.1/addmagic",
"termux-root/data/data/com.termux/files/usr/tmp": "tmp",
"termux-root/data/data/com.termux/files/usr/share": "share",
"termux-root/data/data/com.termux/files/usr/share/man": "share/man",
"termux-root/data/data/com.termux/files/usr/share/man/man1": "share/man/man1",
"termux-root/data/data/com.termux/files/usr/share/man/man1/bed.1": "share/man/man1/bed.1",
"termux-root/data/data/com.termux/files/usr/share/bed": "share/bed"  }
}

